FileFly-0.1.2.dist-info/METADATA
FileFly-0.1.2.dist-info/WHEEL
FileFly-0.1.2.dist-info/license_files/LICENSE
FileFly/__init__.py
FileFly/FileFly.cp312-win_amd64.pyd
FileFly-0.1.2.dist-info/RECORD
