Metadata-Version: 2.3
Name: FileFly
Version: 0.1.2
Classifier: Programming Language :: Rust
Classifier: Programming Language :: Python :: Implementation :: CPython
Classifier: Programming Language :: Python :: Implementation :: PyPy
License-File: LICENSE
Summary: 适用于64位Windows的文件查找工具
Keywords: File,Windows,Find,Find File
Author-email: WebChang <2965330149@qq.com>
Maintainer-email: WebChang <2965330149@qq.com>
Requires-Python: >=3.7
